CHANGES.txt
LICENSE.txt
MANIFEST.in
README.rst
setup.py
js/__init__.py
js.chart.egg-info/PKG-INFO
js.chart.egg-info/SOURCES.txt
js.chart.egg-info/dependency_links.txt
js.chart.egg-info/entry_points.txt
js.chart.egg-info/namespace_packages.txt
js.chart.egg-info/not-zip-safe
js.chart.egg-info/requires.txt
js.chart.egg-info/top_level.txt
js/chart/__init__.py
js/chart/test_chart.txt
js/chart/resources/Chart.js
js/chart/resources/Chart.min.js