Metadata-Version: 1.0
Name: js.chart
Version: 0.2.0
Summary: fanstatic chart.js integration
Home-page: https://github.com/RedTurtle/js.chart
Author: RedTurtle Developers
Author-email: sviluppoplone@redturtle.it
License: BSD
Keywords: chartjs redturtle
Platform: UNKNOWN
